src/barrel.v
// ==============================================================================
// Module Name:  barrel_shifter_16bit
// Description:  A highly structured 16-bit Barrel Shifter with boundary registers.
//               Designed specifically for physical design (PD) flows. 
//               Features stage-by-stage 2:1 MUX structural logic to preserve 
//               predictable data-path routing across stages.
//
// Supported Modes:
//   2'b00 : Logical Left Shift (LSL)
//   2'b01 : Logical Right Shift (LSR)
//   2'b10 : Arithmetic Right Shift (ASR)
//   2'b11 : Rotate Right (ROR)
// ==============================================================================

module barrel_shifter_16bit (
    input  wire        clk,
    input  wire        rst_n,
    input  wire [15:0] din,         // Data input
    input  wire [3:0]  shift_amt,   // Shift amount (0 to 15)
    input  wire [1:0]  mode,        // Shift mode selector
    output reg  [15:0] dout         // Data output (registered)
);

    // --------------------------------------------------------------------------
    // Boundary Input Registers
    // --------------------------------------------------------------------------
    // Registering inputs is crucial for Physical Design. It provides well-defined
    // startpoints for STA (Static Timing Analysis) and prevents external delays
    // from corrupting internal data-path timing.
    // --------------------------------------------------------------------------
    reg [15:0] r_din;
    reg [3:0]  r_shift_amt;
    reg [1:0]  r_mode;

    always @(posedge clk or negedge rst_n) begin
        if (!rst_n) begin
            r_din       <= 16'h0000;
            r_shift_amt <= 4'h0;
            r_mode      <= 2'b00;
        end else begin
            r_din       <= din;
            r_shift_amt <= shift_amt;
            r_mode      <= mode;
        end
    end

    // --------------------------------------------------------------------------
    // Stage-by-Stage Combinational Shifter Core
    // --------------------------------------------------------------------------
    // To make this a great physical design data-path, we build it out of 4 distinct
    // stages of 2:1 multiplexers. This maps beautifully to standard cell libraries
    // and creates a highly structured cell matrix during placement.
    // --------------------------------------------------------------------------
    
    // Internal wires for intermediate stage routing
    wire [15:0] stage0_out; // Output of Stage 0 (Shift-by-1 or 0)
    wire [15:0] stage1_out; // Output of Stage 1 (Shift-by-2 or 0)
    wire [15:0] stage2_out; // Output of Stage 2 (Shift-by-4 or 0)
    wire [15:0] stage3_out; // Output of Stage 3 (Shift-by-8 or 0)

    // Helper sign extension bit for Arithmetic Right Shift (ASR)
    wire sign_bit = r_din[15];

    // ==========================================================================
    // STAGE 0: Shift/Rotate by 1 bit or 0
    // ==========================================================================
    generate
        genvar i;
        for (i = 0; i < 16; i = i + 1) begin : stage0_mux_gen
            assign stage0_out[i] = (r_shift_amt[0] == 1'b0) ? r_din[i] : (
                (r_mode == 2'b00) ? ((i >= 1) ? r_din[i-1] : 1'b0) :         // LSL: Shift Left by 1
                (r_mode == 2'b01) ? ((i <= 14) ? r_din[i+1] : 1'b0) :        // LSR: Shift Right by 1
                (r_mode == 2'b10) ? ((i <= 14) ? r_din[i+1] : sign_bit) :    // ASR: Shift Right with Sign-extend
                                    ((i <= 14) ? r_din[i+1] : r_din[0])      // ROR: Rotate Right (bit 0 wraps to 15)
            );
        end
    endgenerate

    // ==========================================================================
    // STAGE 1: Shift/Rotate by 2 bits or 0
    // ==========================================================================
    generate
        for (i = 0; i < 16; i = i + 1) begin : stage1_mux_gen
            assign stage1_out[i] = (r_shift_amt[1] == 1'b0) ? stage0_out[i] : (
                (r_mode == 2'b00) ? ((i >= 2) ? stage0_out[i-2] : 1'b0) :
                (r_mode == 2'b01) ? ((i <= 13) ? stage0_out[i+2] : 1'b0) :
                (r_mode == 2'b10) ? ((i <= 13) ? stage0_out[i+2] : sign_bit) :
                                    stage0_out[(i+2)%16]
            );
        end
    endgenerate

    // ==========================================================================
    // STAGE 2: Shift/Rotate by 4 bits or 0
    // ==========================================================================
    generate
        for (i = 0; i < 16; i = i + 1) begin : stage2_mux_gen
            assign stage2_out[i] = (r_shift_amt[2] == 1'b0) ? stage1_out[i] : (
                (r_mode == 2'b00) ? ((i >= 4) ? stage1_out[i-4] : 1'b0) :
                (r_mode == 2'b01) ? ((i <= 11) ? stage1_out[i+4] : 1'b0) :
                (r_mode == 2'b10) ? ((i <= 11) ? stage1_out[i+4] : sign_bit) :
                                    stage1_out[(i+4)%16]
            );
        end
    endgenerate

    // ==========================================================================
    // STAGE 3: Shift/Rotate by 8 bits or 0
    // ==========================================================================
    // Note: This stage represents the largest physical routing jump. 
    // In physical design layout, these connections will span across approximately
    // half the physical width of the standard cell matrix.
    // ==========================================================================
    generate
        for (i = 0; i < 16; i = i + 1) begin : stage3_mux_gen
            assign stage3_out[i] = (r_shift_amt[3] == 1'b0) ? stage2_out[i] : (
                (r_mode == 2'b00) ? ((i >= 8) ? stage2_out[i-8] : 1'b0) :
                (r_mode == 2'b01) ? ((i <= 7) ? stage2_out[i+8] : 1'b0) :
                (r_mode == 2'b10) ? ((i <= 7) ? stage2_out[i+8] : sign_bit) :
                                    stage2_out[(i+8)%16]
            );
        end
    endgenerate

    // --------------------------------------------------------------------------
    // Boundary Output Registers
    // --------------------------------------------------------------------------
    // Registering outputs provides clean endpoints for timing constraints, making
    // it easy to close timing margins in place & route tools.
    // --------------------------------------------------------------------------
    always @(posedge clk or negedge rst_n) begin
        if (!rst_n) begin
            dout <= 16'h0000;
        end else begin
            dout <= stage3_out;
        end
    end

endmodule

src/barreltb.v
`timescale 1ns/1ps

module tb_barrel_shifter_16bit;

    // Inputs
    reg         clk;
    reg         rst_n;
    reg  [15:0] din;
    reg  [3:0]  shift_amt;
    reg  [1:0]  mode;

    // Outputs
    wire [15:0] dout;

    // Instantiate the Unit Under Test (UUT)
    barrel_shifter_16bit uut (
        .clk(clk),
        .rst_n(rst_n),
        .din(din),
        .shift_amt(shift_amt),
        .mode(mode),
        .dout(dout)
    );

    // Clock Generation (100 MHz -> Period of 10ns)
    always #5 clk = ~clk;

    // Task for checking actual vs expected with a pipeline delay account
    // Since input is registered and output is registered, there is a 
    // latency of 2 clock cycles from setting 'din' to reading 'dout'.
    task check_output(input [15:0] expected_val, input [15:0] active_input, input [3:0] active_amt, input [1:0] active_mode);
        begin
            @(posedge clk); // Allow pipeline delay to clear
            #1; // Minor offset after clock edge
            if (dout !== expected_val) begin
                $display("[ERROR] Mode: %b, Amt: %d, Din: 16'h%h | Expected: 16'h%h, Got: 16'h%h", 
                          active_mode, active_amt, active_input, expected_val, dout);
            end else begin
                $display("[SUCCESS] Mode: %b, Amt: %d, Din: 16'h%h | Output correctly matches: 16'h%h", 
                          active_mode, active_amt, active_input, dout);
            end
        end
    endtask

    initial begin
        // ----------------------------------------------------------------------
        // VCD File Dump Configuration
        // This is crucial for generating waveforms (.vcd) to analyze in GTKWave 
        // and for conducting power analysis in the Physical Design flow.
        // ----------------------------------------------------------------------
        $dumpfile("tb_barrel_shifter_16bit.vcd");
        $dumpvars(0, tb_barrel_shifter_16bit);

        // Initialize Signals
        clk = 0;
        rst_n = 0;
        din = 16'h0000;
        shift_amt = 4'd0;
        mode = 2'b00;

        // Apply Reset
        #15;
        rst_n = 1;
        #10;

        // ----------------------------------------------------------------------
        // Test Case 1: Logical Left Shift (LSL) - Mode 00
        // Shift 16'hF00F by 4 -> Expected result: 16'h00F0 (after 2 cycles)
        // ----------------------------------------------------------------------
        $display("\n--- Starting Test Case 1: LSL ---");
        din = 16'hF00F; shift_amt = 4'd4; mode = 2'b00;
        @(posedge clk); // Data enters input registers
        @(posedge clk); // Data passes through combinatorial logic to output register
        check_output(16'h00F0, 16'hF00F, 4'd4, 2'b00);

        // ----------------------------------------------------------------------
        // Test Case 2: Logical Right Shift (LSR) - Mode 01
        // Shift 16'hFF00 by 8 -> Expected result: 16'h00FF
        // ----------------------------------------------------------------------
        $display("\n--- Starting Test Case 2: LSR ---");
        din = 16'hFF00; shift_amt = 4'd8; mode = 2'b01;
        @(posedge clk);
        @(posedge clk);
        check_output(16'h00FF, 16'hFF00, 4'd8, 2'b01);

        // ----------------------------------------------------------------------
        // Test Case 3: Arithmetic Right Shift (ASR) - Mode 10 (Negative number)
        // Shift 16'hF000 by 4 -> Expected result: 16'hFF00 (Sign-extended)
        // ----------------------------------------------------------------------
        $display("\n--- Starting Test Case 3: ASR (Negative) ---");
        din = 16'hF000; shift_amt = 4'd4; mode = 2'b10;
        @(posedge clk);
        @(posedge clk);
        check_output(16'hFF00, 16'hF000, 4'd4, 2'b10);

        // ----------------------------------------------------------------------
        // Test Case 4: Rotate Right (ROR) - Mode 11
        // Rotate 16'h000F by 4 -> Expected result: 16'hF000 (Bits wrap around)
        // ----------------------------------------------------------------------
        $display("\n--- Starting Test Case 4: ROR ---");
        din = 16'h000F; shift_amt = 4'd4; mode = 2'b11;
        @(posedge clk);
        @(posedge clk);
        check_output(16'hF000, 16'h000F, 4'd4, 2'b11);

        // ----------------------------------------------------------------------
        // Test Case 5: Shift by 0 (Pass-through test)
        // Shift 16'h1234 by 0 -> Expected result: 16'h1234
        // ----------------------------------------------------------------------
        $display("\n--- Starting Test Case 5: Shift by 0 ---");
        din = 16'h1234; shift_amt = 4'd0; mode = 2'b00;
        @(posedge clk);
        @(posedge clk);
        check_output(16'h1234, 16'h1234, 4'd0, 2'b00);

        $display("\nAll simulation checks finished.");
        $finish;
    end

endmodule

src/tb_barrel_shifter_16bit.vcd
$date
	Sun Jun 28 22:45:04 2026
$end
$version
	Icarus Verilog
$end
$timescale
	1ps
$end
$scope module tb_barrel_shifter_16bit $end
$var wire 16 ! dout [15:0] $end
$var reg 1 " clk $end
$var reg 16 # din [15:0] $end
$var reg 2 $ mode [1:0] $end
$var reg 1 % rst_n $end
$var reg 4 & shift_amt [3:0] $end
$scope module uut $end
$var wire 1 " clk $end
$var wire 16 ' din [15:0] $end
$var wire 2 ( mode [1:0] $end
$var wire 1 % rst_n $end
$var wire 4 ) shift_amt [3:0] $end
$var wire 16 * stage3_out [15:0] $end
$var wire 16 + stage2_out [15:0] $end
$var wire 16 , stage1_out [15:0] $end
$var wire 16 - stage0_out [15:0] $end
$var wire 1 . sign_bit $end
$var reg 16 / dout [15:0] $end
$var reg 16 0 r_din [15:0] $end
$var reg 2 1 r_mode [1:0] $end
$var reg 4 2 r_shift_amt [3:0] $end
$scope begin stage0_mux_gen[0] $end
$var parameter 2 3 i $end
$upscope $end
$scope begin stage0_mux_gen[1] $end
$var parameter 2 4 i $end
$upscope $end
$scope begin stage0_mux_gen[2] $end
$var parameter 3 5 i $end
$upscope $end
$scope begin stage0_mux_gen[3] $end
$var parameter 3 6 i $end
$upscope $end
$scope begin stage0_mux_gen[4] $end
$var parameter 4 7 i $end
$upscope $end
$scope begin stage0_mux_gen[5] $end
$var parameter 4 8 i $end
$upscope $end
$scope begin stage0_mux_gen[6] $end
$var parameter 4 9 i $end
$upscope $end
$scope begin stage0_mux_gen[7] $end
$var parameter 4 : i $end
$upscope $end
$scope begin stage0_mux_gen[8] $end
$var parameter 5 ; i $end
$upscope $end
$scope begin stage0_mux_gen[9] $end
$var parameter 5 < i $end
$upscope $end
$scope begin stage0_mux_gen[10] $end
$var parameter 5 = i $end
$upscope $end
$scope begin stage0_mux_gen[11] $end
$var parameter 5 > i $end
$upscope $end
$scope begin stage0_mux_gen[12] $end
$var parameter 5 ? i $end
$upscope $end
$scope begin stage0_mux_gen[13] $end
$var parameter 5 @ i $end
$upscope $end
$scope begin stage0_mux_gen[14] $end
$var parameter 5 A i $end
$upscope $end
$scope begin stage0_mux_gen[15] $end
$var parameter 5 B i $end
$upscope $end
$scope begin stage1_mux_gen[0] $end
$var parameter 2 C i $end
$upscope $end
$scope begin stage1_mux_gen[1] $end
$var parameter 2 D i $end
$upscope $end
$scope begin stage1_mux_gen[2] $end
$var parameter 3 E i $end
$upscope $end
$scope begin stage1_mux_gen[3] $end
$var parameter 3 F i $end
$upscope $end
$scope begin stage1_mux_gen[4] $end
$var parameter 4 G i $end
$upscope $end
$scope begin stage1_mux_gen[5] $end
$var parameter 4 H i $end
$upscope $end
$scope begin stage1_mux_gen[6] $end
$var parameter 4 I i $end
$upscope $end
$scope begin stage1_mux_gen[7] $end
$var parameter 4 J i $end
$upscope $end
$scope begin stage1_mux_gen[8] $end
$var parameter 5 K i $end
$upscope $end
$scope begin stage1_mux_gen[9] $end
$var parameter 5 L i $end
$upscope $end
$scope begin stage1_mux_gen[10] $end
$var parameter 5 M i $end
$upscope $end
$scope begin stage1_mux_gen[11] $end
$var parameter 5 N i $end
$upscope $end
$scope begin stage1_mux_gen[12] $end
$var parameter 5 O i $end
$upscope $end
$scope begin stage1_mux_gen[13] $end
$var parameter 5 P i $end
$upscope $end
$scope begin stage1_mux_gen[14] $end
$var parameter 5 Q i $end
$upscope $end
$scope begin stage1_mux_gen[15] $end
$var parameter 5 R i $end
$upscope $end
$scope begin stage2_mux_gen[0] $end
$var parameter 2 S i $end
$upscope $end
$scope begin stage2_mux_gen[1] $end
$var parameter 2 T i $end
$upscope $end
$scope begin stage2_mux_gen[2] $end
$var parameter 3 U i $end
$upscope $end
$scope begin stage2_mux_gen[3] $end
$var parameter 3 V i $end
$upscope $end
$scope begin stage2_mux_gen[4] $end
$var parameter 4 W i $end
$upscope $end
$scope begin stage2_mux_gen[5] $end
$var parameter 4 X i $end
$upscope $end
$scope begin stage2_mux_gen[6] $end
$var parameter 4 Y i $end
$upscope $end
$scope begin stage2_mux_gen[7] $end
$var parameter 4 Z i $end
$upscope $end
$scope begin stage2_mux_gen[8] $end
$var parameter 5 [ i $end
$upscope $end
$scope begin stage2_mux_gen[9] $end
$var parameter 5 \ i $end
$upscope $end
$scope begin stage2_mux_gen[10] $end
$var parameter 5 ] i $end
$upscope $end
$scope begin stage2_mux_gen[11] $end
$var parameter 5 ^ i $end
$upscope $end
$scope begin stage2_mux_gen[12] $end
$var parameter 5 _ i $end
$upscope $end
$scope begin stage2_mux_gen[13] $end
$var parameter 5 ` i $end
$upscope $end
$scope begin stage2_mux_gen[14] $end
$var parameter 5 a i $end
$upscope $end
$scope begin stage2_mux_gen[15] $end
$var parameter 5 b i $end
$upscope $end
$scope begin stage3_mux_gen[0] $end
$var parameter 2 c i $end
$upscope $end
$scope begin stage3_mux_gen[1] $end
$var parameter 2 d i $end
$upscope $end
$scope begin stage3_mux_gen[2] $end
$var parameter 3 e i $end
$upscope $end
$scope begin stage3_mux_gen[3] $end
$var parameter 3 f i $end
$upscope $end
$scope begin stage3_mux_gen[4] $end
$var parameter 4 g i $end
$upscope $end
$scope begin stage3_mux_gen[5] $end
$var parameter 4 h i $end
$upscope $end
$scope begin stage3_mux_gen[6] $end
$var parameter 4 i i $end
$upscope $end
$scope begin stage3_mux_gen[7] $end
$var parameter 4 j i $end
$upscope $end
$scope begin stage3_mux_gen[8] $end
$var parameter 5 k i $end
$upscope $end
$scope begin stage3_mux_gen[9] $end
$var parameter 5 l i $end
$upscope $end
$scope begin stage3_mux_gen[10] $end
$var parameter 5 m i $end
$upscope $end
$scope begin stage3_mux_gen[11] $end
$var parameter 5 n i $end
$upscope $end
$scope begin stage3_mux_gen[12] $end
$var parameter 5 o i $end
$upscope $end
$scope begin stage3_mux_gen[13] $end
$var parameter 5 p i $end
$upscope $end
$scope begin stage3_mux_gen[14] $end
$var parameter 5 q i $end
$upscope $end
$scope begin stage3_mux_gen[15] $end
$var parameter 5 r i $end
$upscope $end
$upscope $end
$scope task check_output $end
$var reg 4 s active_amt [3:0] $end
$var reg 16 t active_input [15:0] $end
$var reg 2 u active_mode [1:0] $end
$var reg 16 v expected_val [15:0] $end
$upscope $end
$upscope $end
$enddefinitions $end
$comment Show the parameter values. $end
$dumpall
b1111 r
b1110 q
b1101 p
b1100 o
b1011 n
b1010 m
b1001 l
b1000 k
b111 j
b110 i
b101 h
b100 g
b11 f
b10 e
b1 d
b0 c
b1111 b
b1110 a
b1101 `
b1100 _
b1011 ^
b1010 ]
b1001 \
b1000 [
b111 Z
b110 Y
b101 X
b100 W
b11 V
b10 U
b1 T
b0 S
b1111 R
b1110 Q
b1101 P
b1100 O
b1011 N
b1010 M
b1001 L
b1000 K
b111 J
b110 I
b101 H
b100 G
b11 F
b10 E
b1 D
b0 C
b1111 B
b1110 A
b1101 @
b1100 ?
b1011 >
b1010 =
b1001 <
b1000 ;
b111 :
b110 9
b101 8
b100 7
b11 6
b10 5
b1 4
b0 3
$end
#0
$dumpvars
bx v
bx u
bx t
bx s
b0 2
b0 1
b0 0
b0 /
0.
b0 -
b0 ,
b0 +
b0 *
b0 )
b0 (
b0 '
b0 &
0%
b0 $
b0 #
0"
b0 !
$end
#5000
1"
#10000
0"
#15000
1"
1%
#20000
0"
#25000
b11110000 *
b11110000 +
b1111000000001111 ,
b1111000000001111 -
1.
b100 2
b1111000000001111 0
1"
b100 &
b100 )
b1111000000001111 #
b1111000000001111 '
#30000
0"
#35000
b11110000 !
b11110000 /
b0 u
b100 s
b1111000000001111 t
b11110000 v
1"
#40000
0"
#45000
1"
#46000
b1 $
b1 (
b1000 &
b1000 )
b1111111100000000 #
b1111111100000000 '
#50000
0"
#55000
b1111111100000000 ,
b11111111 *
b1111111100000000 +
b1111111100000000 -
b1 1
b1000 2
b1111111100000000 0
1"
#60000
0"
#65000
b11111111 !
b11111111 /
b1 u
b1000 s
b1111111100000000 t
b11111111 v
1"
#70000
0"
#75000
1"
#76000
b10 $
b10 (
b100 &
b100 )
b1111000000000000 #
b1111000000000000 '
#80000
0"
#85000
b1111000000000000 ,
b1111111100000000 +
b1111111100000000 *
b1111000000000000 -
b10 1
b100 2
b1111000000000000 0
1"
#90000
0"
#95000
b1111111100000000 !
b1111111100000000 /
b10 u
b100 s
b1111000000000000 t
b1111111100000000 v
1"
#100000
0"
#105000
1"
#106000
b11 $
b11 (
b1111 #
b1111 '
#110000
0"
#115000
b1111000000000000 *
b1111000000000000 +
b1111 ,
b1111 -
0.
b11 1
b1111 0
1"
#120000
0"
#125000
b1111000000000000 !
b1111000000000000 /
b11 u
b1111 t
b1111000000000000 v
1"
#130000
0"
#135000
1"
#136000
b0 $
b0 (
b0 &
b0 )
b1001000110100 #
b1001000110100 '
#140000
0"
#145000
b1001000110100 *
b1001000110100 ,
b1001000110100 +
b1001000110100 -
b0 1
b0 2
b1001000110100 0
1"
#150000
0"
#155000
b1001000110100 !
b1001000110100 /
b0 u
b0 s
b1001000110100 t
b1001000110100 v
1"
